{
  "national": {
    "Country": "India",
    "Confirmed": 0,
    "Active": 4302,
    "Recovered": 3281,
    "Deaths": 0,
    "Date": "Home \n\t\t\t\t\n\t\t\t\tNotification\n\t\t\t\t\n\t\t\t\t\tResources\n\t\t\t\n\t\t\t\t\n\t\t\t\t\n\t\t\t\tAwareness\n\t\t\t\tDistrict-wise\n\t\t\t\t\t\tCOVID-19 test positivity rates \n\n\t\t\t\t\n\n\t\t\t\n\t\t\t\n\t\t\t\n\t\t\t\n\t\t\n\n\t\t\n\t\t\t\n\t\t\t\t\n\t\t\t\t\t\n\t\t\t\t\t\t\n\t\t\t\t\t\t\t\n\t\t\t\t\t\t\t\t\n\t\t\t\t\t\t\t\t\t\n\t\t\t\t\t\t\t\t\tIndia\n\t\t\t\t\t\t\t\t\n\t\t\t\t\t\t\t\t\n\t\t\t\t\t\t\t\t\t\n\t\t\t\t\t\t\t\t\t\t हिन्दी \n\t\t\t\t\t\t\t\t\t\n\t\t\t\t\t\t\t\t\t\t\n\n\t\t\t\t\t\t\t\t\t\t\n\t\t\t\t\t\t\t\t\t\t Screen Reader\n\t\t\t\t\t\t\t\t\t\t\t\tAcess \n\t\t\t\t\t\t\t\t\t\t\n\t\t\t\t\t\t\t\t\t\t\t\n\t\t\t\t\t\t\t\t\t\t\t\t\n\t\t\t\t\t\t\t\t\t\t\t\t\n\t\t\t\t\t\t\t\t\t\t\t\t\n\t\t\t\t\t\t\t\t\t\t\t\n\t\t\t\t\t\t\t\t\t\t\t\n\t\t\t\t\t\t\t\t\t\t\t\t\n\t\t\t\t\t\t\t\t\t\t\t\t\n\t\t\t\t\t\t\t\t\t\t\t\tPIB\n\t\t\t\t\t\t\t\t\t\t\t\t\n\t\t\t\t\t\t\t\t\t\t\t\t\n\t\t\t\t\t\t\t\t\t\t\t\t\n\t\t\t\t\t\t\t\t\t\t\t\n\t\t\t\t\t\t\t\t\t\t\n\t\t\t\t\t\t\t\t\t\t\n\t\t\t\t\t\t\t\t\t\t\t\n\t\t\t\t\t\t\t\t\t\t\t\t \n\t\t\t\t\t\t\t\t\t\t\t\n\t\t\t\t\t\t\t\t\t\t\t\t\n\t\t\t\t\t\t\t\t\t\t\t\t\tA+\n\t\t\t\t\t\t\t\t\t\t\t\t\tA\n\t\t\t\t\t\t\t\t\t\t\t\t\tA-\n\t\t\t\t\t\t\t\t\t\t\t\t\n\t\t\t\t\t\t\t\t\t\t\t\n\t\t\t\t\t\t\t\t\t\t\n\t\t\t\t\t\t\t\t\t\t\t\n\t\t\t\t\t\t\t\t\t\t\t\tA\n\t\t\t\t\t\t\t\t\t\t\t\tA\n\t\t\t\t\t\t\t\t\t\t\t\n\t\t\t\t\t\t\t\t\t\t\n\t\t\t\t\t\t\t\t\t\t\n\t\t\t\t\t\t\t\t\t\n\t\t\t\t\t\t\t\t\n\t\t\t\t\t\t\t\n\t\t\t\t\t\t\n\t\t\t\t\t\n\t\t\t\t\n\t\t\t\t\n\t\t\t\t\n\t\t\t\t\t\n\t\t\t\t\t\t\n\t\t\t\t\t\t\t\n\t\t\t\t\t\t\t\t\n\t\t\t\t\t\t\t\t\t\n\t\t\t\t\t\t\t\t\t\t\n\t\t\t\t\t\t\t\t\t\t\n\t\t\t\t\t\t\t\t\t\t\tMinistry of Health  and Family Welfare\n\t\t\t\t\t\t\t\t\t\t\tGovernment of India\n\t\t\t\t\t\t\t\t\t\t\n\t\t\t\t\t\t\t\t\t\n\t\t\t\t\t\t\t\t\t\n\t\t\t\t\t\t\t\t\t\t \n\t\t\t\t\t\t\t\t\t\t\n\t\t\t\t\t\t\t\t\t\t\t\n\t\t\t\t\t\t\t\t\t\t\t\t Home \n\t\t\t\t\t\t\t\t\t\t\t\t\n\t\t\t\t\t\t\t\t\t\t\t\tNotification\n\t\t\t\t\t\t\t\t\t\t\t\t\n\t\t\t\t\t\t\t\t\t\t\t\t\n\t\t\t\t\t\t\t\t\t\t\t\t\tResources\n\t\t\t\t\t\t\t\t\t\t\t\t\n\t\t\t\t\t\t\t\t\t\t\t\t\n\t\t\t\t\t\t\t\t\t\t\t\tVaccination Status\n\t\t\t\t\t\t\t\t\t\t\t\t\nState/UT-wise Covid-19 cases:(6 May 2023 – 31 Dec 2024)\n\t\t\t\t\t\t\t\t\t\t\t\t\nState/UT-wise Covid-19 cases: (31st Jan 2020 to 5th May 2023)\n\n\n\n\t\t\t\t\t\t\t\t\t\t\t\t\n\t\t\t\t\t\t\t\t\t\t\t\t\n\t\t\t\t\t\t\t\t\t\t\t\tAwareness\n\t\t\t\t\t\t\t\t\t\t\t\t\n\t\t\t\t\t\t\t\t\t\t\t\t\n\t\t\t\t\t\t\t\t\t\t\t\t\n\t\t\t\t\t\t\t\t\t\t\t\t\n\n\t\t\t\t\t\t\t\t\t\t\t\t\t\n\t\t\t\t\t\t\t\t\t\t\t\t\n\t\t\t\t\t\t\t\t\t\t\t\t\t\t\n\t\t\t\t\t\t\t\t\t\t\t\t\t\t↓\n\t\t\t\t\t\t\t\t\t\t\t\t\t\t↑\n\t\t\t\t\t\t\t\t\t\t\t\t\t\n\t\t\t\t\t\t\t\t\t\t\t\t\n\n\t\t\t\t\t\t\t\t\t\t\t\n\t\t\t\t\t\t\t\t\t\t\n\t\t\t\t\t\t\t\t\t\n\t\t\t\t\t\t\t\t\n\t\t\t\t\t\t\t\n\t\t\t\t\t\t\n\t\t\t\t\t\n\t\t\t\t\n\t\t\t\t\n\t\t\t\t\t\n\t\t\t\t\t\t\n\t\t\t\t\t\t\t\n\t\t\t\t\t\t\t\t\n\t\t\t\t\t\t\t\t\t\n\t\t\t\t\t\t\t\t\t\t\n\n\t\t\t\t\t\t\t\t\t\t\t\n\n\n\t\t\t\t\t\t\t\t\t\n\t\t\t\t\t\t\t\t\n\t\t\t\t\t\t\t\n\t\t\t\t\t\t\t\n\t\t\t\t\t\t\n\t\t\t\t\t\n\t\t\t\t\n\n\t\t\t\t\n\t\t\t\t\t\n\t\t\t\t\t\t\n\t\t\t\t\t\t\t\n\t\t\t\t\t\t\t\t\n\t\t\t\t\t\t\t\t\n\t\t\t\t\t\t\t\t\tToll Free : 1075\n\t\t\t\t\t\t\t\t\n\t\t\t\t\t\t\t\t\n\t\t\t\t\t\t\t\t\n\t\t\t\t\t\t\t\t\tCovid-19 facilities in States & Union\n\t\t\t\t\t\t\t\t\t\t\tTerritories\n\t\t\t\t\t\t\t\t\n\t\t\t\t\t\t\t\t\n\t\t\t\t\t\t\t\t\tArogya Setu  App \n\t\t\t\t\t\t\t\t\t\t\t \n\t\t\t\t\t\t\t\t\t\t\n\t\t\t\t\t\t\t\t\n\t\t\t\t\t\t\t\n\t\t\t\t\t\t\n\t\t\t\t\t\n\t\t\t\t\n\t\t\t\n\t\t\n\t\t\t\n\n\t\t\t\t\n\t\t\t\t\t\n\t\t\t\t\t\t\n\t\t\t\t\t\t\t\n\n\t\t\t\t\t\t\t\t\n\t\t\t\t\t\t\t\t\tCOVID-19 INDIA as on : 4 June 2025, 08:00 IST (GMT+5:30)\n\t\t\t\t\t\t\t\t\t\t\t\n\t\t\t\t\t\t\t\t\n\t\t\t\t\t\t\t\t\n\t\t\t\t\t\t\t\t\t\n\t\t\t\t\t\t\t\t\t\t\n\t\t\t\t\t\t\t\t\t\t\tActive  (56.40%)\n\t\t\t\t\t\t\t\t\t\t\t4302  \n\t\t\t\t\t\t\t\t\t\t\t\t\n\t\t\t\t\t\t\t\t\t\t\t\n\t\t\t\t\t\t\t\t\t\t\tActive \n\t\t\t\t\t\t\t\t\t\t\t(56.40%) \n\t\t\t\t\t\t\t\t\t\t\t4302  \n\t\t\t\t\t\t\t\t\t\t\t\t\t\n\t\t\t\t\t\t\t\t\t\t\t\n\t\t\t\t\t\t\t\t\t\t\n\t\t\t\t\t\t\t\t\t\t\n\t\t\t\t\t\t\t\t\t\t\tDischarged  (43.02%)\n\t\t\t\t\t\t\t\t\t\t\t3281\n\t\t\t\t\t\t\t\t\t\t\t\n\t\t\t\t\t\t\t\t\t\t\tDischarged \n\t\t\t\t\t\t\t\t\t\t\t(43.02%) \n\t\t\t\t\t\t\t\t\t\t\t3281\n\t\t\t\t\t\t\t\t\t\t\t\t \n\t\t\t\t\t\t\t\t\t\t\n\t\t\t\t\t\t\t\t\t\t\n\t\t\t\t\t\t\t\t\t\n\t\t\t\t\t\t\t\t\n\t\t\t\t\t\t\t\t\n\t\t\t\t\t\t\t\t\t\n\t\t\t\t\t\t\t\t\t\t\n\t\t\t\t\t\t\t\t\t\t\t\n\t\t\t\t\t\t\t\t\t\t\t\n\t\t\t\t\t\t\t\t\t\t\t\n\t\t\t\t\t\t\t\t\t\t\n\t\t\t\t\t\t\t\t\t\n\t\t\t\t\t\t\t\t\n\n\t\t\t\t\t\t\t\n\t\t\t\t\t\t\t\n\t\t\t\t\t\t\t\n\t\t\t\t\t\t\t\n\t\t\t\t\t\t\t\n\t\t\t\t\t\t\n\t\t\t\t\n\n\t\t\t\t\n\t\t\t\t\t\n\t\t\t\t\t\t\n\t\t\t\t\t\t\t\n\t\t\t\t\t\t\t\t\n\t\t\t\t\t\t\t\t\t\n\t\t\t\t\t\t\t\t\t\t\n\n\t\t\t\t\t\t\t\t\t\t\t\n\n\n\t\t\t\t\t\t\t\t\t\n\t\t\t\t\t\t\t\t\n\t\t\t\t\t\t\t\n\t\t\t\t\t\t\t\n\t\t\t\t\t\t\n\t\t\t\t\t\n\t\t\t\t\n\n\t\t\t\t\n\t\t\t\t\n\n\t\t\t\t\n\t\t\t\t\t\n\t\t\t\t\t\t\n\t\t\t\t\t\t\t\n\t\t\t\t\t\t\t\t COVID-19 Statewise Status \n\t\t\t\t\t\t\t\t\n\t\t\t\t\t\t\t\t\tCOVID-19 INDIA as on : 4 June 2025, 08:00 IST (GMT+5:30)\n\t\t\t\t\t\t\t\t\t\t\t\t\n\t\t\t\t\t\t\t\t\t\t\n\t\t\t\t\t\t\t\t\t\t\t\n\t\t\t\t\t\t\t\t\t\t\t\t\n\t\t\t\t\t\t\t\t\t\t\t\n\t\t\t\t\t\t\t\t\t\t\t\n\t\t\t\t\t\t\t\t\t\t\t\tS. No.\n\t\t\t\t\t\t\t\t\t\t\t\tName of State / UT\n\t\t\t\t\t\t\t\t\t\t\t\t\n\t\t\t\t\t\t\t\t\t\t\t\tActive\n\t\t\t\t\t\t\t\t\t\t\t\t\t\tCases\n\n\t\t\t\t\t\t\t\t\t\t\t\t\n\t\t\t\t\t\t\t\t\t\t\t\t\tCured/Discharged/Migrated\n\t\t\t\t\t\t\t\t\t\t\t\t\n\t\t\t\t\t\t\t\t\t\t\t\t\n\t\t\t\t\t\t\t\t\t\t\t\t\tDeaths* (Details of causes below)\n\t\t\t\t\t\t\t\t\t\t\t\t\n\t\t\t\t\t\t\t\t\t\t\t\n\t\t\t\t\t\t\t\t\t\t\t\n\t\t\t\t\t\t\t\t\t\t\t\tTotal\n\t\t\t\t\t\t\t\t\t\t\t\tChange since\n\t\t\t\t\t\t\t\t\t\t\t\t\t\tyesterday\n\t\t\t\t\t\t\t\t\t\t\t\t\tChange since yesterday\n\t\t\t\t\t\t\t\t\t\t\t\t\n\t\t\t\t\t\t\t\t\t\t\t\tCumulative since 1st January 2025 \n\t\t\t\t\t\t\t\t\t\t\t\tChange since yesterday\n\t\t\t\t\t\t\t\t\t\t\t\tCumulative since 1st January 2025 \n\t\t\t\t\t\t\t\t\t\t\t\n\t\t\t\t\t\t\t\t\t\t\t\n\t\t\t\t\t\t\t\t\t\t\t\tDeath Since yesterday\n\t\t\t\t\t\t\t\t\t\t\t\n\n\t\t\t\t\t\t\t\t\t\t\n\n\n\t\t\t\t\t\t\t\t\t\t\n\t\t\t\t\t\t\t\t\t1Andhra Pradesh31 3  17 5  0   2Arunachal Pradesh0   3 0  0   3Assam8 2  1 1  0   4Bihar22 11  4 4  0   5Chandigarh2   0 0  0   6Chhattisgarh15 4  5 0  0   7Delhi457 64  602 39  5 1  8Goa8   7 1  0   9Gujarat461 64  199 43  2 1  10Haryana51 7  35 9  0   11Himachal Pradesh1 1  0 0  0   12Jammu and Kashmir6 3  4 3  0   13Jharkhand9 2  3 2  0   14Karnataka324 13  254 40  4   15Kerala***1373 43  1175 287  9   16Madhya Pradesh22 1  7 0  1   17Maharashtra510 16  435 66  14 4  18Mizoram2   0 0  0   19Odisha18 3  0 0  0   20Puducherry22 5  70 12  0   21Punjab12 3  5 0  1   22Rajasthan90 15  46 9  1   23Sikkim4   18 0  0   24Tamil Nadu216 1  268 29  4 1  25Telangana3 1  3 1  0   26Uttarakhand2 1  15 2  0   27Uttar Pradesh201 63  39 0  2   28West Bengal432 60  66 28  1   Total# 4302 276   3281  581  44 7 *Delhi (1 death)- 22 years old female with Old treated Pulmonary Koch's, B/L lower respiratort tract infection, Covid pnemonia, shock, Type 1 Respiratory failure.*Maharashtra (4 deaths) - 1) 55 years old male with H/O Cardiac Arrythmia and was on antiarrythimics. Patient is also a known case of COPD with chronic bronchitis. (2) 73 years old male with Cardiogenic Shock,Parkinson's Disease, Covid 19 pneumonia, Hypertension. (3) 23 years old female with Diabetes Mellitus, HTN. (4) 27 years old male with IHD with old PTB, LRTI, alcohol withdrawal seizure.*Tamil Nadu (1 death)-76 years old male with Acute Respiratory Distress Syndrome (ARDS), COVID-19 pneumonia, and sepsis with multi-organ dysfunction syndrome (MODS).*Gujarat (1 Death) - Details awaited.\n\t\t\t\t\t\t\t\t\n\t\t\t\t\t\t\t\n\t\t\t\t\t\t\n\t\t\t\t\t\n\t\t\t\t\n\n\t\t\t\t\n\t\t\t\t\t\n\t\t\t\t\t\t\n\t\t\t\t\t\t\t\n\t\t\t\t\t\t\t\t\n\t\t\t\t\t\t\t\t\t\n\t\t\t\t\t\t\t\t\t\tAwareness\n\t\t\t\t\t\t\t\t\t\t\n\t\t\t\t\t\t\t\t\t\t\tEnglish\n\t\t\t\t\t\t\t\t\t\t\tHindi\n\t\t\t\t\t\t\t\t\t\t\n\t\t\t\t\t\t\t\t\t\n\t\t\t\t\t\t\t\t\t\n\t\t\t\t\t\t\t\t\t\t\n\t\t\t\t\t\t\t\t\t\t\t\n\t\t\t\t\t\t\t\t\t\t\t\t\n\t\t\t\t\t\t\t\t\t\t\t\t\t\n\t\t\t\t\t\t\t\t\t\t\t\t\t\t\n\t\t\t\t\t\t\t\t\t\t\t\t\t\n\t\t\t\t\t\t\t\t\t\t\t\t\t\n\t\t\t\t\t\t\t\t\t\t\t\t\n\t\t\t\t\t\t\t\t\t\t\t\n\t\t\t\t\t\t\t\t\t\t\n\t\t\t\t\t\t\t\t\t\t\n\t\t\t\t\t\t\t\t\t\t\t\n\t\t\t\t\t\t\t\t\t\t\t\t\n\t\t\t\t\t\t\t\t\t\t\t\t\t\n\t\t\t\t\t\t\t\t\t\t\t\t\t\t\n\t\t\t\t\t\t\t\t\t\t\t\t\t\n\t\t\t\t\t\t\t\t\t\t\t\t\n\t\t\t\t\t\t\t\t\t\t\t\n\t\t\t\t\t\t\t\t\t\t\n\t\t\t\t\t\t\t\t\t\t\n\t\t\t\t\t\t\t\t\t\t\t\n\t\t\t\t\t\t\t\t\t\t\t\t\n\t\t\t\t\t\t\t\t\t\t\t\t\t\n\t\t\t\t\t\t\t\t\t\t\t\t\t\t\n\t\t\t\t\t\t\t\t\t\t\t\t\t\n\t\t\t\t\t\t\t\t\t\t\t\t\n\t\t\t\t\t\t\t\t\t\t\t\n\t\t\t\t\t\t\t\t\t\t\n\t\t\t\t\t\t\t\t\t\t\n\t\t\t\t\t\t\t\t\t\t\t\n\t\t\t\t\t\t\t\t\t\t\t\t\n\t\t\t\t\t\t\t\t\t\t\t\t\t\n\t\t\t\t\t\t\t\t\t\t\t\t\t\t\n\t\t\t\t\t\t\t\t\t\t\t\t\t\n\t\t\t\t\t\t\t\t\t\t\t\t\n\t\t\t\t\t\t\t\t\t\t\t\n\t\t\t\t\t\t\t\t\t\t\n\t\t\t\t\t\t\t\t\t\t\n\t\t\t\t\t\t\t\t\t\t\t\n\t\t\t\t\t\t\t\t\t\t\t\t\n\t\t\t\t\t\t\t\t\t\t\t\t\t\n\t\t\t\t\t\t\t\t\t\t\t\t\t\t\n\t\t\t\t\t\t\t\t\t\t\t\t\t\n\t\t\t\t\t\t\t\t\t\t\t\t\n\t\t\t\t\t\t\t\t\t\t\t\n\t\t\t\t\t\t\t\t\t\t\n\t\t\t\t\t\t\t\t\t\t\n\t\t\t\t\t\t\t\t\t\t\t\n\t\t\t\t\t\t\t\t\t\t\t\t\n\t\t\t\t\t\t\t\t\t\t\t\t\t\n\t\t\t\t\t\t\t\t\t\t\t\t\t\t\n\t\t\t\t\t\t\t\t\t\t\t\t\t\n\t\t\t\t\t\t\t\t\t\t\t\t\n\t\t\t\t\t\t\t\t\t\t\t\n\t\t\t\t\t\t\t\t\t\t\n\t\t\t\t\t\t\t\t\t\t\n\t\t\t\t\t\t\t\t\t\t\n\t\t\t\t\t\t\t\t\t\t\n\t\t\t\t\t\t\t\t\t\t\t\n\t\t\t\t\t\t\t\t\t\t\t\t\n\t\t\t\t\t\t\t\t\t\t\t\t\t\n\t\t\t\t\t\t\t\t\t\t\t\t\t\t\n\t\t\t\t\t\t\t\t\t\t\t\t\t\n\t\t\t\t\t\t\t\t\t\t\t\t\n\t\t\t\t\t\t\t\t\t\t\t\n\t\t\t\t\t\t\t\t\t\t\n\t\t\t\t\t\t\t\t\t\t\n\t\t\t\t\t\t\t\t\t\t\t\n\t\t\t\t\t\t\t\t\t\t\t\t\n\t\t\t\t\t\t\t\t\t\t\t\t\t\n\t\t\t\t\t\t\t\t\t\t\t\t\t\t\n\t\t\t\t\t\t\t\t\t\t\t\t\t\n\t\t\t\t\t\t\t\t\t\t\t\t\n\t\t\t\t\t\t\t\t\t\t\t\n\t\t\t\t\t\t\t\t\t\t\n\t\t\t\t\t\t\t\t\t\n\t\t\t\t\t\t\t\t\n\t\t\t\t\t\t\t\n\t\t\t\t\t\t\n\t\t\t\t\t\n\t\t\t\t\n\n\n\t\t\t\t\n\t\t\t\t\t\n\t\t\t\t\t\t\n\t\t\t\t\t\t\t\n\t\t\t\t\t\t\t\t\n\t\t\t\t\t\t\t\t\t\n\t\t\t\t\t\t\t\t\n\t\t\t\t\t\t\t\n\t\t\t\t\t\t\n\t\t\t\t\t\n\t\t\t\t\n\n\t\t\t\n\n\t\t\t\n\t\t\t\t\n\t\t\t\t\t\n\t\t\t\t\t\t\n\t\t\t\t\t\t\t\n\t\t\t\t\t\t\t\t\n\t\t\t\t\t\t\t\t\tDisclaimer : \n\t\t\t\t\t\t\t\t\tWebsite content managed by Ministry of Health and Family\n\t\t\t\t\t\t\t\t\t\tWelfare, GOI\n\t\t\t\t\t\t\t\t\tDesign, Developed and Hosted by National Informatics Centre (NIC)"
  },
  "stateData": [
    {
      "state": "Andhra Pradesh",
      "confirmed": 0,
      "active": 31,
      "recovered": 3,
      "deaths": 3,
      "lastUpdated": "2025-06-04T04:22:20.944Z"
    },
    {
      "state": "Arunachal Pradesh",
      "confirmed": 0,
      "active": 0,
      "recovered": 3,
      "deaths": 0,
      "lastUpdated": "2025-06-04T04:22:20.946Z"
    },
    {
      "state": "Assam",
      "confirmed": 0,
      "active": 8,
      "recovered": 2,
      "deaths": 2,
      "lastUpdated": "2025-06-04T04:22:20.946Z"
    },
    {
      "state": "Bihar",
      "confirmed": 0,
      "active": 22,
      "recovered": 11,
      "deaths": 11,
      "lastUpdated": "2025-06-04T04:22:20.946Z"
    },
    {
      "state": "Chandigarh",
      "confirmed": 0,
      "active": 2,
      "recovered": 0,
      "deaths": 0,
      "lastUpdated": "2025-06-04T04:22:20.946Z"
    },
    {
      "state": "Chhattisgarh",
      "confirmed": 0,
      "active": 15,
      "recovered": 4,
      "deaths": 4,
      "lastUpdated": "2025-06-04T04:22:20.946Z"
    },
    {
      "state": "Delhi",
      "confirmed": 0,
      "active": 457,
      "recovered": 64,
      "deaths": 64,
      "lastUpdated": "2025-06-04T04:22:20.946Z"
    },
    {
      "state": "Goa",
      "confirmed": 0,
      "active": 8,
      "recovered": 7,
      "deaths": 1,
      "lastUpdated": "2025-06-04T04:22:20.946Z"
    },
    {
      "state": "Gujarat",
      "confirmed": 0,
      "active": 461,
      "recovered": 64,
      "deaths": 64,
      "lastUpdated": "2025-06-04T04:22:20.946Z"
    },
    {
      "state": "Haryana",
      "confirmed": 0,
      "active": 51,
      "recovered": 7,
      "deaths": 7,
      "lastUpdated": "2025-06-04T04:22:20.946Z"
    },
    {
      "state": "Himachal Pradesh",
      "confirmed": 0,
      "active": 1,
      "recovered": 1,
      "deaths": 1,
      "lastUpdated": "2025-06-04T04:22:20.946Z"
    },
    {
      "state": "Jammu and Kashmir",
      "confirmed": 0,
      "active": 6,
      "recovered": 3,
      "deaths": 3,
      "lastUpdated": "2025-06-04T04:22:20.946Z"
    },
    {
      "state": "Jharkhand",
      "confirmed": 0,
      "active": 9,
      "recovered": 2,
      "deaths": 2,
      "lastUpdated": "2025-06-04T04:22:20.946Z"
    },
    {
      "state": "Karnataka",
      "confirmed": 0,
      "active": 324,
      "recovered": 13,
      "deaths": 13,
      "lastUpdated": "2025-06-04T04:22:20.946Z"
    },
    {
      "state": "Kerala***",
      "confirmed": 0,
      "active": 1373,
      "recovered": 43,
      "deaths": 43,
      "lastUpdated": "2025-06-04T04:22:20.946Z"
    },
    {
      "state": "Madhya Pradesh",
      "confirmed": 0,
      "active": 22,
      "recovered": 1,
      "deaths": 1,
      "lastUpdated": "2025-06-04T04:22:20.946Z"
    },
    {
      "state": "Maharashtra",
      "confirmed": 0,
      "active": 510,
      "recovered": 16,
      "deaths": 16,
      "lastUpdated": "2025-06-04T04:22:20.946Z"
    },
    {
      "state": "Mizoram",
      "confirmed": 0,
      "active": 2,
      "recovered": 0,
      "deaths": 0,
      "lastUpdated": "2025-06-04T04:22:20.946Z"
    },
    {
      "state": "Odisha",
      "confirmed": 0,
      "active": 18,
      "recovered": 3,
      "deaths": 3,
      "lastUpdated": "2025-06-04T04:22:20.946Z"
    },
    {
      "state": "Puducherry",
      "confirmed": 0,
      "active": 22,
      "recovered": 5,
      "deaths": 5,
      "lastUpdated": "2025-06-04T04:22:20.946Z"
    },
    {
      "state": "Punjab",
      "confirmed": 0,
      "active": 12,
      "recovered": 3,
      "deaths": 3,
      "lastUpdated": "2025-06-04T04:22:20.946Z"
    },
    {
      "state": "Rajasthan",
      "confirmed": 0,
      "active": 90,
      "recovered": 15,
      "deaths": 15,
      "lastUpdated": "2025-06-04T04:22:20.946Z"
    },
    {
      "state": "Sikkim",
      "confirmed": 0,
      "active": 4,
      "recovered": 18,
      "deaths": 0,
      "lastUpdated": "2025-06-04T04:22:20.946Z"
    },
    {
      "state": "Tamil Nadu",
      "confirmed": 0,
      "active": 216,
      "recovered": 1,
      "deaths": 1,
      "lastUpdated": "2025-06-04T04:22:20.946Z"
    },
    {
      "state": "Telangana",
      "confirmed": 0,
      "active": 3,
      "recovered": 1,
      "deaths": 1,
      "lastUpdated": "2025-06-04T04:22:20.946Z"
    },
    {
      "state": "Uttarakhand",
      "confirmed": 0,
      "active": 2,
      "recovered": 1,
      "deaths": 1,
      "lastUpdated": "2025-06-04T04:22:20.946Z"
    },
    {
      "state": "Uttar Pradesh",
      "confirmed": 0,
      "active": 201,
      "recovered": 63,
      "deaths": 63,
      "lastUpdated": "2025-06-04T04:22:20.946Z"
    },
    {
      "state": "West Bengal",
      "confirmed": 0,
      "active": 432,
      "recovered": 60,
      "deaths": 60,
      "lastUpdated": "2025-06-04T04:22:20.946Z"
    },
    {
      "state": "4302",
      "confirmed": 0,
      "active": 276,
      "recovered": 276,
      "deaths": 3281,
      "lastUpdated": "2025-06-04T04:22:20.946Z"
    }
  ]
}